titbit/__init__.py
titbit/ast_utils.py
titbit/graphs.py
titbit/mappings.py
titbit/strings.py
titbit-0.1.10.dist-info/LICENSE
titbit-0.1.10.dist-info/METADATA
titbit-0.1.10.dist-info/WHEEL
titbit-0.1.10.dist-info/top_level.txt
titbit-0.1.10.dist-info/RECORD
