Metadata-Version: 2.1
Name: titbit
Version: 0.1.10
Summary: A place to dump might-be-useful-again code as an alternative of leaving in a notebook where it will never be found again
Home-page: https://github.com/i2mint/titbit
License: apache-2.0
License-File: LICENSE
Requires-Dist: lkj
Requires-Dist: i2
Requires-Dist: meshed
Requires-Dist: dol
Requires-Dist: graphviz
